{"index.md":"01748a4a","src_algorithm_algorithmqa_01-快速排序.md":"3e447660","src_algorithm_handlewriting_01-遍历数组方法.md":"1f1b8fda","src_essay_2022_everyday_01-箭头函数和普通函数有什么区别.md":"65b079d8","src_essay_2022_everyday_02-说一下css盒模型.md":"90cc7342","src_essay_2022_everyday_03-如何判断一个数组是数组.md":"eaafbde0","src_essay_2022_everyday_04-颜色拾取器windows失焦bug.md":"c40f084f","src_essay_2022_everyday_05-使用export具名导出和默认导出区别.md":"2ff0b1f0","src_essay_2022_everyday_06_css的display双值.md":"9f72085e","src_essay_2022_life_01-随风而去.md":"e383d728","src_essay_2022_technology_01-前端程序员自我修养.md":"c7c99206","src_note_issue_01-ts-issue.md":"eea88e98","src_note_issue_02-vue-issue.md":"d7414c5b","src_note_issue_03-webview-issue.md":"ccb4fba0","src_note_issue_04-react-issue.md":"a83239dc","src_note_issue_05-node-issue.md":"a0146574","src_note_issue_06-webpack-issue.md":"f3695a0b","src_note_issue_07-git-issue.md":"8c5d07cd","src_note_issue_08-css-issue.md":"17d624b1","src_note_issue_09-js-issue.md":"022c194b","src_note_issue_10-http-issue.md":"334d117d","src_note_issue_11-browser-issue.md":"4a4096d9","src_note_issue_12-algorithm-issue.md":"0139ab0b","src_note_issue_13-other-issue.md":"b23d2d86","src_note_notes_electron_01-vite初始化electron.md":"bee1c643","src_note_notes_linux_01-vim常用命令.md":"f19b8e67","src_note_notes_nestjs_01-初识nestjs.md":"1902e9ad","src_note_notes_react_01-react基础.md":"b86ae990","src_note_notes_typescript_01-泛型.md":"27cb02b7","src_note_notes_typescript_02-测试.md":"df508c07","src_read_2022_life_01-穷爸爸富爸爸.md":"1e32c126","src_read_2022_technology_javascripthighdesign_01-javascripthighdesign.md":"388c809f","src_read_2022_technology_javascripthighdesign_02-javascripthighdesign.md":"dfd8b5e3","src_read_2022_technology_vuedesign_01-vuedesign.md":"c3b1c4f9"}
